interpylate_fls/__init__.py
interpylate_fls/data.py
interpylate_fls/logger.py
interpylate_fls/neuralnetwork.py
interpylate_fls/plotter.py
interpylate_fls-0.0.0.dist-info/licenses/LICENSE
interpylate_fls-0.0.0.dist-info/METADATA
interpylate_fls-0.0.0.dist-info/WHEEL
interpylate_fls-0.0.0.dist-info/top_level.txt
interpylate_fls-0.0.0.dist-info/RECORD
