Metadata-Version: 2.4
Name: interpylate-fls
Version: 0.0.0
Summary: A Python package for training neural networks on 5-dimensional datasets for interpolation tasks
Author-email: Funmi Looi-Somoye <OL306@cam.ac.uk>
License: MIT
Project-URL: Homepage, https://github.com/FunmiLS/Neural-Network-Interpolator
Project-URL: Documentation, https://c1-neural-network-interpolator.readthedocs.io/en/latest/
Project-URL: Repository, https://github.com/FunmiLS/Neural-Network-Interpolator
Keywords: neural-network,machine-learning,interpolation,pytorch,regression,5d-data
Classifier: Development Status :: 3 - Alpha
Classifier: Intended Audience :: Science/Research
Classifier: Intended Audience :: Developers
Classifier: License :: OSI Approved :: MIT License
Classifier: Programming Language :: Python :: 3
Classifier: Programming Language :: Python :: 3.9
Classifier: Programming Language :: Python :: 3.10
Classifier: Programming Language :: Python :: 3.11
Classifier: Topic :: Scientific/Engineering :: Artificial Intelligence
Classifier: Topic :: Software Development :: Libraries :: Python Modules
Requires-Python: >=3.9
License-File: LICENSE
Requires-Dist: torch>=2.2.0
Requires-Dist: scikit-learn>=1.6.0
Requires-Dist: pandas>=2.3.0
Requires-Dist: numpy<2.0.0,>=1.26.0
Requires-Dist: matplotlib>=3.9.0
Requires-Dist: seaborn>=0.13.0
Provides-Extra: dev
Requires-Dist: pytest>=7.0.0; extra == "dev"
Requires-Dist: pytest-cov>=4.0.0; extra == "dev"
Requires-Dist: black>=23.0.0; extra == "dev"
Requires-Dist: flake8>=6.0.0; extra == "dev"
Requires-Dist: mypy>=1.0.0; extra == "dev"
Provides-Extra: docs
Requires-Dist: sphinx>=5.0.0; extra == "docs"
Requires-Dist: sphinx-autodoc-typehints>=1.19.0; extra == "docs"
Dynamic: license-file
